sol_structs/__init__.py
sol_structs-1.0.3.dist-info/METADATA
sol_structs-1.0.3.dist-info/WHEEL
sol_structs-1.0.3.dist-info/RECORD
